src/verilog/basic/gates.v
// =============================================================================
// Basic Logic Gates - Fundamental Building Blocks
// =============================================================================
// Description:
//   This module implements fundamental logic gates (AND, OR, NOT, NAND, NOR, 
//   XOR, XNOR) with parameterized bit-widths. These are the atomic building 
//   blocks of all digital circuits.
//
// Learning Points:
//   - Verilog module syntax and parameters
//   - Continuous assignment with 'assign'
//   - Bitwise operators (&, |, ~, ^)
//   - Parameterized designs for reusability
//
// Author: ARM7 Computer System Project
// Date: 2025-11-03
// =============================================================================

// AND Gate - Output is 1 only when all inputs are 1
module and_gate #(
    parameter WIDTH = 1  // Bit-width of inputs/outputs
) (
    input  wire [WIDTH-1:0] a,    // First input
    input  wire [WIDTH-1:0] b,    // Second input
    output wire [WIDTH-1:0] y     // Output: a AND b
);
    // Bitwise AND operation
    // For each bit position i: y[i] = a[i] & b[i]
    assign y = a & b;
endmodule

// OR Gate - Output is 1 when at least one input is 1
module or_gate #(
    parameter WIDTH = 1
) (
    input  wire [WIDTH-1:0] a,
    input  wire [WIDTH-1:0] b,
    output wire [WIDTH-1:0] y     // Output: a OR b
);
    // Bitwise OR operation
    assign y = a | b;
endmodule

// NOT Gate (Inverter) - Output is the complement of input
module not_gate #(
    parameter WIDTH = 1
) (
    input  wire [WIDTH-1:0] a,
    output wire [WIDTH-1:0] y     // Output: NOT a
);
    // Bitwise NOT operation (inversion)
    assign y = ~a;
endmodule

// NAND Gate - NOT-AND, output is 0 only when all inputs are 1
module nand_gate #(
    parameter WIDTH = 1
) (
    input  wire [WIDTH-1:0] a,
    input  wire [WIDTH-1:0] b,
    output wire [WIDTH-1:0] y     // Output: NOT(a AND b)
);
    // NAND is universal gate - can build any logic function
    assign y = ~(a & b);
endmodule

// NOR Gate - NOT-OR, output is 1 only when all inputs are 0
module nor_gate #(
    parameter WIDTH = 1
) (
    input  wire [WIDTH-1:0] a,
    input  wire [WIDTH-1:0] b,
    output wire [WIDTH-1:0] y     // Output: NOT(a OR b)
);
    // NOR is also a universal gate
    assign y = ~(a | b);
endmodule

// XOR Gate - Exclusive OR, output is 1 when inputs differ
module xor_gate #(
    parameter WIDTH = 1
) (
    input  wire [WIDTH-1:0] a,
    input  wire [WIDTH-1:0] b,
    output wire [WIDTH-1:0] y     // Output: a XOR b
);
    // XOR is useful for parity, comparison, and arithmetic
    // Truth table: 0^0=0, 0^1=1, 1^0=1, 1^1=0
    assign y = a ^ b;
endmodule

// XNOR Gate - Exclusive NOR, output is 1 when inputs are equal
module xnor_gate #(
    parameter WIDTH = 1
) (
    input  wire [WIDTH-1:0] a,
    input  wire [WIDTH-1:0] b,
    output wire [WIDTH-1:0] y     // Output: NOT(a XOR b)
);
    // XNOR is an equality detector
    // Truth table: 0~^0=1, 0~^1=0, 1~^0=0, 1~^1=1
    assign y = ~(a ^ b);
endmodule

// Multi-input AND Gate - Output is 1 only when all inputs are 1
module and_n #(
    parameter WIDTH = 1,      // Bit-width of each input
    parameter NUM_INPUTS = 4  // Number of inputs
) (
    input  wire [NUM_INPUTS-1:0][WIDTH-1:0] inputs,  // Array of inputs
    output wire [WIDTH-1:0] y                         // Output
);
    // Reduction AND across all inputs
    // This demonstrates how to handle variable number of inputs
    wire [WIDTH-1:0] result [NUM_INPUTS-1:0];
    
    assign result[0] = inputs[0];
    
    genvar i;
    generate
        for (i = 1; i < NUM_INPUTS; i = i + 1) begin : and_chain
            assign result[i] = result[i-1] & inputs[i];
        end
    endgenerate
    
    assign y = result[NUM_INPUTS-1];
endmodule

// Multi-input OR Gate - Output is 1 when at least one input is 1
module or_n #(
    parameter WIDTH = 1,
    parameter NUM_INPUTS = 4
) (
    input  wire [NUM_INPUTS-1:0][WIDTH-1:0] inputs,
    output wire [WIDTH-1:0] y
);
    wire [WIDTH-1:0] result [NUM_INPUTS-1:0];
    
    assign result[0] = inputs[0];
    
    genvar i;
    generate
        for (i = 1; i < NUM_INPUTS; i = i + 1) begin : or_chain
            assign result[i] = result[i-1] | inputs[i];
        end
    endgenerate
    
    assign y = result[NUM_INPUTS-1];
endmodule

// Buffer - Passes input to output (useful for signal isolation)
module buffer #(
    parameter WIDTH = 1
) (
    input  wire [WIDTH-1:0] a,
    output wire [WIDTH-1:0] y
);
    // Simple pass-through
    // In real hardware, buffers provide drive strength and isolation
    assign y = a;
endmodule

// Tri-state Buffer - Output can be high-impedance (Z)
module tri_buffer #(
    parameter WIDTH = 1
) (
    input  wire [WIDTH-1:0] a,      // Data input
    input  wire             enable, // Enable signal
    output wire [WIDTH-1:0] y       // Output (Z when disabled)
);
    // When enable=1, output = input
    // When enable=0, output = high-impedance (Z)
    // Tri-state buffers are used for shared buses
    assign y = enable ? a : {WIDTH{1'bz}};
endmodule

// =============================================================================
// Usage Examples:
// =============================================================================
// 
// Example 1: 8-bit AND gate
//   and_gate #(.WIDTH(8)) my_and (
//       .a(8'b10101010),
//       .b(8'b11001100),
//       .y(result)  // result = 8'b10001000
//   );
//
// Example 2: Single-bit XOR (useful for parity)
//   xor_gate #(.WIDTH(1)) parity_gen (
//       .a(bit1),
//       .b(bit2),
//       .y(parity)
//   );
//
// Example 3: 4-input AND gate
//   and_n #(.WIDTH(1), .NUM_INPUTS(4)) multi_and (
//       .inputs({in0, in1, in2, in3}),
//       .y(all_high)
//   );
//
// =============================================================================

src/verilog/basic/gates_tb.v
// =============================================================================
// Basic Logic Gates Testbench
// =============================================================================
// Description:
//   Comprehensive testbench for all basic logic gates. Tests single-bit and
//   multi-bit operations, verifies truth tables, and checks edge cases.
//
// Learning Points:
//   - Testbench structure and organization
//   - Initial blocks and test stimulus generation
//   - Self-checking testbenches with assertions
//   - Waveform generation for debugging
//
// Author: ARM7 Computer System Project
// Date: 2025-11-03
// =============================================================================

`timescale 1ns/1ps

module gates_tb;
    // Test signals
    reg  [7:0] a, b;
    wire [7:0] and_out, or_out, not_out, nand_out, nor_out, xor_out, xnor_out;
    wire [7:0] buf_out, tri_out;
    reg        tri_enable;
    
    // Test counters
    integer errors = 0;
    integer tests = 0;
    
    // Instantiate all gates with 8-bit width
    and_gate #(.WIDTH(8)) dut_and (
        .a(a), .b(b), .y(and_out)
    );
    
    or_gate #(.WIDTH(8)) dut_or (
        .a(a), .b(b), .y(or_out)
    );
    
    not_gate #(.WIDTH(8)) dut_not (
        .a(a), .y(not_out)
    );
    
    nand_gate #(.WIDTH(8)) dut_nand (
        .a(a), .b(b), .y(nand_out)
    );
    
    nor_gate #(.WIDTH(8)) dut_nor (
        .a(a), .b(b), .y(nor_out)
    );
    
    xor_gate #(.WIDTH(8)) dut_xor (
        .a(a), .b(b), .y(xor_out)
    );
    
    xnor_gate #(.WIDTH(8)) dut_xnor (
        .a(a), .b(b), .y(xnor_out)
    );
    
    buffer #(.WIDTH(8)) dut_buf (
        .a(a), .y(buf_out)
    );
    
    tri_buffer #(.WIDTH(8)) dut_tri (
        .a(a), .enable(tri_enable), .y(tri_out)
    );
    
    // Task to check a result and report errors
    task check_result;
        input [7:0] expected;
        input [7:0] actual;
        input [80*8-1:0] test_name;
        begin
            tests = tests + 1;
            if (expected !== actual) begin
                errors = errors + 1;
                $display("ERROR: %s", test_name);
                $display("  Expected: 0x%02h, Got: 0x%02h", expected, actual);
            end else begin
                $display("PASS: %s", test_name);
            end
        end
    endtask
    
    // Main test sequence
    initial begin
        $display("=================================================");
        $display("Basic Logic Gates Testbench");
        $display("=================================================");
        
        // Initialize signals
        a = 8'h00;
        b = 8'h00;
        tri_enable = 1'b0;
        #10;
        
        // Test 1: All zeros
        $display("\nTest 1: All zeros (0x00 & 0x00)");
        a = 8'h00; b = 8'h00; #10;
        check_result(8'h00, and_out,  "AND: 0x00 & 0x00 = 0x00");
        check_result(8'h00, or_out,   "OR:  0x00 | 0x00 = 0x00");
        check_result(8'hFF, not_out,  "NOT: ~0x00 = 0xFF");
        check_result(8'hFF, nand_out, "NAND: ~(0x00 & 0x00) = 0xFF");
        check_result(8'hFF, nor_out,  "NOR: ~(0x00 | 0x00) = 0xFF");
        check_result(8'h00, xor_out,  "XOR: 0x00 ^ 0x00 = 0x00");
        check_result(8'hFF, xnor_out, "XNOR: ~(0x00 ^ 0x00) = 0xFF");
        
        // Test 2: All ones
        $display("\nTest 2: All ones (0xFF & 0xFF)");
        a = 8'hFF; b = 8'hFF; #10;
        check_result(8'hFF, and_out,  "AND: 0xFF & 0xFF = 0xFF");
        check_result(8'hFF, or_out,   "OR:  0xFF | 0xFF = 0xFF");
        check_result(8'h00, not_out,  "NOT: ~0xFF = 0x00");
        check_result(8'h00, nand_out, "NAND: ~(0xFF & 0xFF) = 0x00");
        check_result(8'h00, nor_out,  "NOR: ~(0xFF | 0xFF) = 0x00");
        check_result(8'h00, xor_out,  "XOR: 0xFF ^ 0xFF = 0x00");
        check_result(8'hFF, xnor_out, "XNOR: ~(0xFF ^ 0xFF) = 0xFF");
        
        // Test 3: Mixed values
        $display("\nTest 3: Mixed values (0xAA & 0x55)");
        a = 8'hAA; b = 8'h55; #10;
        check_result(8'h00, and_out,  "AND: 0xAA & 0x55 = 0x00");
        check_result(8'hFF, or_out,   "OR:  0xAA | 0x55 = 0xFF");
        check_result(8'h55, not_out,  "NOT: ~0xAA = 0x55");
        check_result(8'hFF, nand_out, "NAND: ~(0xAA & 0x55) = 0xFF");
        check_result(8'h00, nor_out,  "NOR: ~(0xAA | 0x55) = 0x00");
        check_result(8'hFF, xor_out,  "XOR: 0xAA ^ 0x55 = 0xFF");
        check_result(8'h00, xnor_out, "XNOR: ~(0xAA ^ 0x55) = 0x00");
        
        // Test 4: Another mixed pattern
        $display("\nTest 4: Pattern (0xF0 & 0x0F)");
        a = 8'hF0; b = 8'h0F; #10;
        check_result(8'h00, and_out,  "AND: 0xF0 & 0x0F = 0x00");
        check_result(8'hFF, or_out,   "OR:  0xF0 | 0x0F = 0xFF");
        check_result(8'h0F, not_out,  "NOT: ~0xF0 = 0x0F");
        check_result(8'hFF, xor_out,  "XOR: 0xF0 ^ 0x0F = 0xFF");
        
        // Test 5: Partial overlap
        $display("\nTest 5: Partial overlap (0xCC & 0xAA)");
        a = 8'hCC; b = 8'hAA; #10;
        check_result(8'h88, and_out,  "AND: 0xCC & 0xAA = 0x88");
        check_result(8'hEE, or_out,   "OR:  0xCC | 0xAA = 0xEE");
        check_result(8'h66, xor_out,  "XOR: 0xCC ^ 0xAA = 0x66");
        
        // Test 6: Buffer
        $display("\nTest 6: Buffer");
        a = 8'h5A; #10;
        check_result(8'h5A, buf_out, "BUFFER: 0x5A -> 0x5A");
        a = 8'hA5; #10;
        check_result(8'hA5, buf_out, "BUFFER: 0xA5 -> 0xA5");
        
        // Test 7: Tri-state buffer
        $display("\nTest 7: Tri-state buffer");
        a = 8'h42;
        tri_enable = 1'b1; #10;
        check_result(8'h42, tri_out, "TRI-STATE (enabled): 0x42 -> 0x42");
        
        tri_enable = 1'b0; #10;
        if (tri_out === 8'hzz) begin
            $display("PASS: TRI-STATE (disabled): Output is high-Z");
            tests = tests + 1;
        end else begin
            $display("ERROR: TRI-STATE (disabled): Expected high-Z, got 0x%02h", tri_out);
            errors = errors + 1;
            tests = tests + 1;
        end
        
        // Test 8: Random patterns
        $display("\nTest 8: Random patterns");
        repeat (10) begin
            a = $random;
            b = $random;
            #10;
            // Verify basic properties
            if ((and_out & a) !== and_out) begin
                $display("ERROR: AND output not subset of input a");
                errors = errors + 1;
            end
            if ((or_out | a) !== or_out) begin
                $display("ERROR: OR output not superset of input a");
                errors = errors + 1;
            end
            if ((not_out ^ a) !== 8'hFF) begin
                $display("ERROR: NOT output incorrect");
                errors = errors + 1;
            end
            tests = tests + 3;
        end
        $display("Random pattern tests completed");
        
        // Test 9: Identity and complement laws
        $display("\nTest 9: Boolean algebra laws");
        a = 8'hA5; b = 8'h00; #10;
        check_result(8'h00, and_out, "Identity: A & 0 = 0");
        
        a = 8'hA5; b = 8'hFF; #10;
        check_result(8'hA5, and_out, "Identity: A & 1 = A");
        check_result(8'hFF, or_out,  "Identity: A | 1 = 1");
        
        a = 8'hA5; b = 8'hA5; #10;
        check_result(8'hA5, and_out, "Idempotent: A & A = A");
        check_result(8'hA5, or_out,  "Idempotent: A | A = A");
        check_result(8'h00, xor_out, "Complement: A ^ A = 0");
        
        // Summary
        $display("\n=================================================");
        $display("Test Summary");
        $display("=================================================");
        $display("Total tests: %0d", tests);
        $display("Passed:      %0d", tests - errors);
        $display("Failed:      %0d", errors);
        
        if (errors == 0) begin
            $display("\nALL TESTS PASSED!");
        end else begin
            $display("\nSOME TESTS FAILED!");
        end
        $display("=================================================");
        
        $finish;
    end
    
    // Waveform dump for debugging
    initial begin
        $dumpfile("gates_tb.vcd");
        $dumpvars(0, gates_tb);
    end
    
endmodule

gates_tb.vcd
$date
	Wed Nov 26 09:57:22 2025
$end
$version
	Icarus Verilog
$end
$timescale
	1ps
$end
$scope module gates_tb $end
$var wire 8 ! xor_out [7:0] $end
$var wire 8 " xnor_out [7:0] $end
$var wire 8 # tri_out [7:0] $end
$var wire 8 $ or_out [7:0] $end
$var wire 8 % not_out [7:0] $end
$var wire 8 & nor_out [7:0] $end
$var wire 8 ' nand_out [7:0] $end
$var wire 8 ( buf_out [7:0] $end
$var wire 8 ) and_out [7:0] $end
$var reg 8 * a [7:0] $end
$var reg 8 + b [7:0] $end
$var reg 1 , tri_enable $end
$var integer 32 - errors [31:0] $end
$var integer 32 . tests [31:0] $end
$scope module dut_and $end
$var wire 8 / a [7:0] $end
$var wire 8 0 b [7:0] $end
$var wire 8 1 y [7:0] $end
$var parameter 32 2 WIDTH $end
$upscope $end
$scope module dut_buf $end
$var wire 8 3 a [7:0] $end
$var wire 8 4 y [7:0] $end
$var parameter 32 5 WIDTH $end
$upscope $end
$scope module dut_nand $end
$var wire 8 6 a [7:0] $end
$var wire 8 7 b [7:0] $end
$var wire 8 8 y [7:0] $end
$var parameter 32 9 WIDTH $end
$upscope $end
$scope module dut_nor $end
$var wire 8 : a [7:0] $end
$var wire 8 ; b [7:0] $end
$var wire 8 < y [7:0] $end
$var parameter 32 = WIDTH $end
$upscope $end
$scope module dut_not $end
$var wire 8 > a [7:0] $end
$var wire 8 ? y [7:0] $end
$var parameter 32 @ WIDTH $end
$upscope $end
$scope module dut_or $end
$var wire 8 A a [7:0] $end
$var wire 8 B b [7:0] $end
$var wire 8 C y [7:0] $end
$var parameter 32 D WIDTH $end
$upscope $end
$scope module dut_tri $end
$var wire 8 E a [7:0] $end
$var wire 1 , enable $end
$var wire 8 F y [7:0] $end
$var parameter 32 G WIDTH $end
$upscope $end
$scope module dut_xnor $end
$var wire 8 H a [7:0] $end
$var wire 8 I b [7:0] $end
$var wire 8 J y [7:0] $end
$var parameter 32 K WIDTH $end
$upscope $end
$scope module dut_xor $end
$var wire 8 L a [7:0] $end
$var wire 8 M b [7:0] $end
$var wire 8 N y [7:0] $end
$var parameter 32 O WIDTH $end
$upscope $end
$scope task check_result $end
$var reg 8 P actual [7:0] $end
$var reg 8 Q expected [7:0] $end
$var reg 640 R test_name [639:0] $end
$upscope $end
$upscope $end
$enddefinitions $end
$comment Show the parameter values. $end
$dumpall
b1000 O
b1000 K
b1000 G
b1000 D
b1000 @
b1000 =
b1000 9
b1000 5
b1000 2
$end
#0
$dumpvars
bx R
bx Q
bx P
b0 N
b0 M
b0 L
b11111111 J
b0 I
b0 H
bz F
b0 E
b0 C
b0 B
b0 A
b11111111 ?
b0 >
b11111111 <
b0 ;
b0 :
b11111111 8
b0 7
b0 6
b0 4
b0 3
b0 1
b0 0
b0 /
b0 .
b0 -
0,
b0 +
b0 *
b0 )
b0 (
b11111111 '
b11111111 &
b11111111 %
b0 $
bz #
b11111111 "
b0 !
$end
#20000
b0 '
b0 8
b0 &
b0 <
b11111111 )
b11111111 1
b0 %
b0 ?
b11111111 $
b11111111 C
b11111111 +
b11111111 0
b11111111 7
b11111111 ;
b11111111 B
b11111111 I
b11111111 M
b11111111 (
b11111111 4
b11111111 *
b11111111 /
b11111111 3
b11111111 6
b11111111 :
b11111111 >
b11111111 A
b11111111 E
b11111111 H
b11111111 L
b111 .
b10110000100111001001111010100100011101000100000011111100010100000110000011110000011000000110000001000000101111000100000001100000111100000110000001100000010100100100000001111010010000000110000011110000100011001000110 R
b11111111 P
b11111111 Q
#30000
b11111111 '
b11111111 8
b0 "
b0 J
b0 )
b0 1
b1010101 %
b1010101 ?
b11111111 !
b11111111 N
b1010101 +
b1010101 0
b1010101 7
b1010101 ;
b1010101 B
b1010101 I
b1010101 M
b10101010 (
b10101010 4
b10101010 *
b10101010 /
b10101010 3
b10101010 6
b10101010 :
b10101010 >
b10101010 A
b10101010 E
b10101010 H
b10101010 L
b11111111 P
b11111111 Q
b1110 .
b10110000100111001001111010100100011101000100000011111100010100000110000011110000100011001000110001000000101111000100000001100000111100001000110010001100010100100100000001111010010000000110000011110000100011001000110 R
#40000
b1111 %
b1111 ?
b1111 +
b1111 0
b1111 7
b1111 ;
b1111 B
b1111 I
b1111 M
b11110000 (
b11110000 4
b11110000 *
b11110000 /
b11110000 3
b11110000 6
b11110000 :
b11110000 >
b11110000 A
b11110000 E
b11110000 H
b11110000 L
b10101 .
b10110000100111001001111010100100011101000100000011111100010100000110000011110000100000101000001001000000101111000100000001100000111100000110101001101010010100100100000001111010010000000110000011110000011000000110000 R
b0 P
b0 Q
#50000
b1110111 '
b1110111 8
b10001 &
b10001 <
b10011001 "
b10011001 J
b10001000 )
b10001000 1
b110011 %
b110011 ?
b11101110 $
b11101110 C
b1100110 !
b1100110 N
b10101010 +
b10101010 0
b10101010 7
b10101010 ;
b10101010 B
b10101010 I
b10101010 M
b11001100 (
b11001100 4
b11001100 *
b11001100 /
b11001100 3
b11001100 6
b11001100 :
b11001100 >
b11001100 A
b11001100 E
b11001100 H
b11001100 L
b11111111 P
b11111111 Q
b11001 .
b101100001001111010100100011101000100000001100000111100001000110001100000010000001011110001000000011000001111000001100000100011000100000001111010010000000110000011110000100011001000110 R
#60000
b11110101 '
b11110101 8
b101 &
b101 <
b1111 "
b1111 J
b1010 )
b1010 1
b10100101 %
b10100101 ?
b11111010 $
b11111010 C
b11110000 !
b11110000 N
b1011010 (
b1011010 4
b1011010 *
b1011010 /
b1011010 3
b1011010 6
b1011010 :
b1011010 >
b1011010 A
b1011010 E
b1011010 H
b1011010 L
b11100 .
b101100001001111010100100011101000100000001100000111100001000011010000110010000001011110001000000011000001111000010000010100000100100000001111010010000000110000011110000011011000110110 R
b1100110 P
b1100110 Q
#70000
b1011111 '
b1011111 8
b1010000 &
b1010000 <
b11110000 "
b11110000 J
b10100000 )
b10100000 1
b1011010 %
b1011010 ?
b10101111 $
b10101111 C
b1111 !
b1111 N
b10100101 (
b10100101 4
b10100101 *
b10100101 /
b10100101 3
b10100101 6
b10100101 :
b10100101 >
b10100101 A
b10100101 E
b10100101 H
b10100101 L
b11101 .
b100001001010101010001100100011001000101010100100011101000100000001100000111100000110101010000010010000000101101001111100010000000110000011110000011010101000001 R
b1011010 P
b1011010 Q
#80000
b11111101 '
b11111101 8
b10101 &
b10101 <
b10111 "
b10111 J
b1000010 #
b1000010 F
b10 )
b10 1
b10111101 %
b10111101 ?
b11101010 $
b11101010 C
b11101000 !
b11101000 N
1,
b1000010 (
b1000010 4
b1000010 *
b1000010 /
b1000010 3
b1000010 6
b1000010 :
b1000010 >
b1000010 A
b1000010 E
b1000010 H
b1000010 L
b11110 .
b100001001010101010001100100011001000101010100100011101000100000001100000111100001000001001101010010000000101101001111100010000000110000011110000100000100110101 R
b10100101 P
b10100101 Q
#90000
bz #
bz F
0,
b11111 .
b10101000101001001001001001011010101001101010100010000010101010001000101001000000010100001100101011011100110000101100010011011000110010101100100001010010011101000100000001100000111100000110100001100100010000000101101001111100010000000110000011110000011010000110010 R
b1000010 P
b1000010 Q
#100000
b11111111 '
b11111111 8
b1011010 &
b1011010 <
b1011010 "
b1011010 J
b0 )
b0 1
b11011011 %
b11011011 ?
b10100101 $
b10100101 C
b10100101 !
b10100101 N
b10000001 +
b10000001 0
b10000001 7
b10000001 ;
b10000001 B
b10000001 I
b10000001 M
b100100 (
b100100 4
b100100 *
b100100 /
b100100 3
b100100 6
b100100 :
b100100 >
b100100 A
b100100 E
b100100 H
b100100 L
b100000 .
#110000
b11111110 '
b11111110 8
b10010100 &
b10010100 <
b10010101 "
b10010101 J
b1 )
b1 1
b11110110 %
b11110110 ?
b1101011 $
b1101011 C
b1101010 !
b1101010 N
b1100011 +
b1100011 0
b1100011 7
b1100011 ;
b1100011 B
b1100011 I
b1100011 M
b1001 (
b1001 4
b1001 *
b1001 /
b1001 3
b1001 6
b1001 :
b1001 >
b1001 A
b1001 E
b1001 H
b1001 L
b100011 .
#120000
b11110010 '
b11110010 8
b1110010 &
b1110010 <
b1111111 "
b1111111 J
b1101 )
b1101 1
b11110010 %
b11110010 ?
b10001101 $
b10001101 C
b10000000 !
b10000000 N
b10001101 +
b10001101 0
b10001101 7
b10001101 ;
b10001101 B
b10001101 I
b10001101 M
b1101 (
b1101 4
b1101 *
b1101 /
b1101 3
b1101 6
b1101 :
b1101 >
b1101 A
b1101 E
b1101 H
b1101 L
b100110 .
#130000
b11111111 '
b11111111 8
b10001000 &
b10001000 <
b10001000 "
b10001000 J
b0 )
b0 1
b10011010 %
b10011010 ?
b1110111 $
b1110111 C
b1110111 !
b1110111 N
b10010 +
b10010 0
b10010 7
b10010 ;
b10010 B
b10010 I
b10010 M
b1100101 (
b1100101 4
b1100101 *
b1100101 /
b1100101 3
b1100101 6
b1100101 :
b1100101 >
b1100101 A
b1100101 E
b1100101 H
b1100101 L
b101001 .
#140000
b11111110 '
b11111110 8
b11110010 &
b11110010 <
b11110011 "
b11110011 J
b1 )
b1 1
b11111110 %
b11111110 ?
b1101 $
b1101 C
b1100 !
b1100 N
b1101 +
b1101 0
b1101 7
b1101 ;
b1101 B
b1101 I
b1101 M
b1 (
b1 4
b1 *
b1 /
b1 3
b1 6
b1 :
b1 >
b1 A
b1 E
b1 H
b1 L
b101100 .
#150000
b11001011 '
b11001011 8
b10000000 &
b10000000 <
b10110100 "
b10110100 J
b110100 )
b110100 1
b10001001 %
b10001001 ?
b1111111 $
b1111111 C
b1001011 !
b1001011 N
b111101 +
b111101 0
b111101 7
b111101 ;
b111101 B
b111101 I
b111101 M
b1110110 (
b1110110 4
b1110110 *
b1110110 /
b1110110 3
b1110110 6
b1110110 :
b1110110 >
b1110110 A
b1110110 E
b1110110 H
b1110110 L
b101111 .
#160000
b1110011 '
b1110011 8
b10010 &
b10010 <
b10011110 "
b10011110 J
b10001100 )
b10001100 1
b10010 %
b10010 ?
b11101101 $
b11101101 C
b1100001 !
b1100001 N
b10001100 +
b10001100 0
b10001100 7
b10001100 ;
b10001100 B
b10001100 I
b10001100 M
b11101101 (
b11101101 4
b11101101 *
b11101101 /
b11101101 3
b11101101 6
b11101101 :
b11101101 >
b11101101 A
b11101101 E
b11101101 H
b11101101 L
b110010 .
#170000
b111111 '
b111111 8
b0 &
b0 <
b11000000 "
b11000000 J
b11000000 )
b11000000 1
b110 %
b110 ?
b11111111 $
b11111111 C
b111111 !
b111111 N
b11000110 +
b11000110 0
b11000110 7
b11000110 ;
b11000110 B
b11000110 I
b11000110 M
b11111001 (
b11111001 4
b11111001 *
b11111001 /
b11111001 3
b11111001 6
b11111001 :
b11111001 >
b11111001 A
b11111001 E
b11111001 H
b11111001 L
b110101 .
#180000
b1111111 '
b1111111 8
b10000 &
b10000 <
b10010000 "
b10010000 J
b10000000 )
b10000000 1
b111010 %
b111010 ?
b11101111 $
b11101111 C
b1101111 !
b1101111 N
b10101010 +
b10101010 0
b10101010 7
b10101010 ;
b10101010 B
b10101010 I
b10101010 M
b11000101 (
b11000101 4
b11000101 *
b11000101 /
b11000101 3
b11000101 6
b11000101 :
b11000101 >
b11000101 A
b11000101 E
b11000101 H
b11000101 L
b111000 .
#190000
b10011010 '
b10011010 8
b1000 &
b1000 <
b1101101 "
b1101101 J
b1100101 )
b1100101 1
b11010 %
b11010 ?
b11110111 $
b11110111 C
b10010010 !
b10010010 N
b1110111 +
b1110111 0
b1110111 7
b1110111 ;
b1110111 B
b1110111 I
b1110111 M
b11100101 (
b11100101 4
b11100101 *
b11100101 /
b11100101 3
b11100101 6
b11100101 :
b11100101 >
b11100101 A
b11100101 E
b11100101 H
b11100101 L
b111011 .
#200000
b11111111 '
b11111111 8
b1011010 &
b1011010 <
b1011010 "
b1011010 J
b0 )
b0 1
b1011010 %
b1011010 ?
b10100101 $
b10100101 C
b10100101 !
b10100101 N
b0 +
b0 0
b0 7
b0 ;
b0 B
b0 I
b0 M
b10100101 (
b10100101 4
b10100101 *
b10100101 /
b10100101 3
b10100101 6
b10100101 :
b10100101 >
b10100101 A
b10100101 E
b10100101 H
b10100101 L
b111110 .
#210000
b1011010 '
b1011010 8
b0 &
b0 <
b10100101 "
b10100101 J
b10100101 )
b10100101 1
b11111111 $
b11111111 C
b1011010 !
b1011010 N
b11111111 +
b11111111 0
b11111111 7
b11111111 ;
b11111111 B
b11111111 I
b11111111 M
b111111 .
b1001001011001000110010101101110011101000110100101110100011110010011101000100000010000010010000000100110001000000011000000100000001111010010000000110000 R
b0 P
b0 Q
#220000
b1011010 &
b1011010 <
b11111111 "
b11111111 J
b10100101 $
b10100101 C
b0 !
b0 N
b10100101 +
b10100101 0
b10100101 7
b10100101 ;
b10100101 B
b10100101 I
b10100101 M
b1000001 .
b1001001011001000110010101101110011101000110100101110100011110010011101000100000010000010010000001111100001000000011000100100000001111010010000000110001 R
b11111111 P
b11111111 Q
#230000
b1000100 .
b10000110110111101101101011100000110110001100101011011010110010101101110011101000011101000100000010000010010000001011110001000000100000100100000001111010010000000110000 R
b0 P
b0 Q
